ctm_git_exposure/__init__.py
ctm_git_exposure/cli.py
ctm_git_exposure/core.py
ctm_git_exposure_scanner-1.0.0.dist-info/licenses/LICENSE
ctm_git_exposure_scanner-1.0.0.dist-info/METADATA
ctm_git_exposure_scanner-1.0.0.dist-info/WHEEL
ctm_git_exposure_scanner-1.0.0.dist-info/entry_points.txt
ctm_git_exposure_scanner-1.0.0.dist-info/top_level.txt
ctm_git_exposure_scanner-1.0.0.dist-info/RECORD
