Metadata-Version: 2.4
Name: ctm-git-exposure-scanner
Version: 1.0.0
Summary: Git Exposure Scanner - Extract sensitive information from exposed .git directories
Author: Moovendhan V
Requires-Python: >=3.8
License-File: LICENSE
Requires-Dist: requests
Dynamic: license-file
